odoo8_addon_dead_mans_switch_server-8.0.1.0.0.99.dev54-py3.8-nspkg.pth
odoo_addons/dead_mans_switch_server/README.rst
odoo_addons/dead_mans_switch_server/__init__.py
odoo_addons/dead_mans_switch_server/__openerp__.py
odoo_addons/dead_mans_switch_server/controllers/__init__.py
odoo_addons/dead_mans_switch_server/controllers/main.py
odoo_addons/dead_mans_switch_server/data/ir_cron.xml
odoo_addons/dead_mans_switch_server/i18n/am.po
odoo_addons/dead_mans_switch_server/i18n/ar.po
odoo_addons/dead_mans_switch_server/i18n/bg.po
odoo_addons/dead_mans_switch_server/i18n/bs.po
odoo_addons/dead_mans_switch_server/i18n/ca.po
odoo_addons/dead_mans_switch_server/i18n/ca_ES.po
odoo_addons/dead_mans_switch_server/i18n/cs.po
odoo_addons/dead_mans_switch_server/i18n/da.po
odoo_addons/dead_mans_switch_server/i18n/da_DK.po
odoo_addons/dead_mans_switch_server/i18n/de.po
odoo_addons/dead_mans_switch_server/i18n/dead_mans_switch_server.pot
odoo_addons/dead_mans_switch_server/i18n/el_GR.po
odoo_addons/dead_mans_switch_server/i18n/en_GB.po
odoo_addons/dead_mans_switch_server/i18n/es.po
odoo_addons/dead_mans_switch_server/i18n/es_AR.po
odoo_addons/dead_mans_switch_server/i18n/es_CL.po
odoo_addons/dead_mans_switch_server/i18n/es_CO.po
odoo_addons/dead_mans_switch_server/i18n/es_CR.po
odoo_addons/dead_mans_switch_server/i18n/es_DO.po
odoo_addons/dead_mans_switch_server/i18n/es_EC.po
odoo_addons/dead_mans_switch_server/i18n/es_ES.po
odoo_addons/dead_mans_switch_server/i18n/es_MX.po
odoo_addons/dead_mans_switch_server/i18n/es_PE.po
odoo_addons/dead_mans_switch_server/i18n/es_PY.po
odoo_addons/dead_mans_switch_server/i18n/es_VE.po
odoo_addons/dead_mans_switch_server/i18n/et.po
odoo_addons/dead_mans_switch_server/i18n/eu.po
odoo_addons/dead_mans_switch_server/i18n/eu_ES.po
odoo_addons/dead_mans_switch_server/i18n/fa.po
odoo_addons/dead_mans_switch_server/i18n/fi.po
odoo_addons/dead_mans_switch_server/i18n/fr.po
odoo_addons/dead_mans_switch_server/i18n/fr_CA.po
odoo8_addon_dead_mans_switch_server-8.0.1.0.0.99.dev54.dist-info/METADATA
odoo8_addon_dead_mans_switch_server-8.0.1.0.0.99.dev54.dist-info/WHEEL
odoo8_addon_dead_mans_switch_server-8.0.1.0.0.99.dev54.dist-info/namespace_packages.txt
odoo8_addon_dead_mans_switch_server-8.0.1.0.0.99.dev54.dist-info/top_level.txt
odoo8_addon_dead_mans_switch_server-8.0.1.0.0.99.dev54.dist-info/RECORD
